README.md
setup.py
bitgov/__init__.py
bitgov/development.py
bitgov/network.py
bitgov.egg-info/PKG-INFO
bitgov.egg-info/SOURCES.txt
bitgov.egg-info/dependency_links.txt
bitgov.egg-info/top_level.txt
bitgov/protocol/__init__.py
bitgov/protocol/client.py
bitgov/protocol/server.py