Metadata-Version: 2.1
Name: bitgov
Version: 0.1.3
Summary: An application layer protocol for the establishment of decentralized democracy.
Home-page: https://github.com/jgphilpott/bitgov
Author: Jacob Philpott
Author-email: jacob.philpott@gmx.com
License: MIT
Platform: UNKNOWN
